camera_fusion/Camera.py
camera_fusion/CameraCorrected.py
camera_fusion/CamerasFusion.py
camera_fusion/__init__.py
camera_fusion-0.0.8.data/scripts/camera_calibration
camera_fusion-0.0.8.data/scripts/cameras_fusion
camera_fusion-0.0.8.dist-info/METADATA
camera_fusion-0.0.8.dist-info/RECORD
camera_fusion-0.0.8.dist-info/WHEEL
camera_fusion-0.0.8.dist-info/top_level.txt
camera_fusion-0.0.8.dist-info/zip-safe
