Metadata-Version: 2.1
Name: camera-fusion
Version: 0.0.8
Summary: Multiple cameras calibration and fusion with OpenCV Python.
Home-page: https://github.com/a1rb4Ck/camera-fusion
Author: Pierre Nagorny
Author-email: pierre.nagorny@univ-smb.fr
License: MIT
Keywords: opencv fusion image video
Platform: UNKNOWN
Classifier: Development Status :: 3 - Alpha
Classifier: Intended Audience :: Developers
Classifier: Intended Audience :: Education
Classifier: Intended Audience :: Science/Research
Classifier: Programming Language :: Python :: 3
Classifier: Programming Language :: Python :: 3.6
Classifier: Programming Language :: Python :: 3.7
Classifier: License :: OSI Approved :: MIT License
Classifier: Operating System :: OS Independent
Classifier: Topic :: Software Development :: Libraries
Classifier: Topic :: Software Development :: Libraries :: Python Modules
Classifier: Topic :: Multimedia :: Video
Classifier: Topic :: Multimedia :: Video :: Capture
Requires-Dist: numpy (>=1.15.3)
Requires-Dist: opencv-contrib-python (>=3.4.3.18)
Requires-Dist: sortednp (>=0.2.0)
